mentabotix-0.1.7.8.dist-info/METADATA
mentabotix-0.1.7.8.dist-info/WHEEL
mentabotix-0.1.7.8.dist-info/entry_points.txt
mentabotix-0.1.7.8.dist-info/licenses/LICENSE
mentabotix/__init__.py
mentabotix/modules/botix.py
mentabotix/modules/exceptions.py
mentabotix/modules/logger.py
mentabotix/modules/menta.py
mentabotix/tools/composers.py
mentabotix/tools/generators.py
mentabotix/tools/selectors.py
mentabotix-0.1.7.8.dist-info/RECORD
