Metadata-Version: 2.1
Name: mentabotix
Version: 0.1.7.8
Summary: A Bot control lib
Author-Email: Whth <88489697+Whth@users.noreply.github.com>
License: MIT
Requires-Python: >=3.11
Requires-Dist: coloredlogs>=15.0.1
Requires-Dist: numpy>=2.0.0
Requires-Dist: terminaltables>=3.1.10
Requires-Dist: bdmc>=0.2.6
Requires-Dist: colorama>=0.4.6
